advlog/__init__.py
advlog-1.0.8.dist-info/LICENSE
advlog-1.0.8.dist-info/METADATA
advlog-1.0.8.dist-info/WHEEL
advlog-1.0.8.dist-info/top_level.txt
advlog-1.0.8.dist-info/RECORD
