Metadata-Version: 2.1
Name: advlog
Version: 1.0.8
Summary: "Advanced logger inspired by other languages' standard logging classes (e.g. Java and Kotlin)."
Home-page: https://github.com/Kiruse/PyAdvancedLogger
Author: Kiruse
Author-email: neurokiruse@outlook.com
License: MIT
Keywords: log,logger,logging
Platform: UNKNOWN
Requires-Python: >=3.0
